tracking_challenge_demo/__init__.py
tracking_challenge_demo/_reader.py
tracking_challenge_demo/_version.py
tracking_challenge_demo/_widget.py
tracking_challenge_demo/_writer.py
tracking_challenge_demo/napari.yaml
tracking_challenge_demo/_tests/__init__.py
tracking_challenge_demo/_tests/test_reader.py
tracking_challenge_demo/_tests/test_widget.py
tracking_challenge_demo/_tests/test_writer.py
tracking_challenge_demo-0.0.8.dist-info/LICENSE
tracking_challenge_demo-0.0.8.dist-info/METADATA
tracking_challenge_demo-0.0.8.dist-info/WHEEL
tracking_challenge_demo-0.0.8.dist-info/entry_points.txt
tracking_challenge_demo-0.0.8.dist-info/top_level.txt
tracking_challenge_demo-0.0.8.dist-info/RECORD
