Metadata-Version: 2.1
Name: tracking-challenge-demo
Version: 0.0.8
Summary: A demo plugin to load, segment and save tracking challenge data.
Home-page: https://github.com/DragaDoncila/tracking-challenge-demo
Author: Draga Doncila
Author-email: ddoncila@gmail.com
License: BSD-3-Clause
Project-URL: Bug Tracker, https://github.com/DragaDoncila/tracking-challenge-demo/issues
Project-URL: Documentation, https://github.com/DragaDoncila/tracking-challenge-demo#README.md
Project-URL: Source Code, https://github.com/DragaDoncila/tracking-challenge-demo
Project-URL: User Support, https://github.com/DragaDoncila/tracking-challenge-demo/issues
Classifier: Development Status :: 2 - Pre-Alpha
Classifier: Framework :: napari
Classifier: Intended Audience :: Developers
Classifier: License :: OSI Approved :: BSD License
Classifier: Operating System :: OS Independent
Classifier: Programming Language :: Python
Classifier: Programming Language :: Python :: 3
Classifier: Programming Language :: Python :: 3 :: Only
Classifier: Programming Language :: Python :: 3.8
Classifier: Programming Language :: Python :: 3.9
Classifier: Programming Language :: Python :: 3.10
Classifier: Topic :: Software Development :: Testing
Requires-Python: >=3.8
License-File: LICENSE
Requires-Dist: dask[array]
Requires-Dist: imagecodecs
Requires-Dist: napari
Requires-Dist: napari-plugin-engine >=0.1.4
Requires-Dist: numpy
Requires-Dist: scikit-image
Requires-Dist: tifffile
Provides-Extra: testing
Requires-Dist: napari ; extra == 'testing'
Requires-Dist: pyqt5 ; extra == 'testing'
Requires-Dist: pytest ; extra == 'testing'
Requires-Dist: pytest-cov ; extra == 'testing'
Requires-Dist: pytest-qt ; extra == 'testing'
Requires-Dist: tox ; extra == 'testing'
